fafi/__init__.py
fafi/appdata.py
fafi/core.py
fafi/db.py
fafi/import_firefox.py
fafi/import_list.py
fafi/input.py
fafi/main.py
fafi-0.2.4.dist-info/METADATA
fafi-0.2.4.dist-info/WHEEL
fafi-0.2.4.dist-info/entry_points.txt
fafi-0.2.4.dist-info/RECORD
