Metadata-Version: 2.1
Name: fafi
Version: 0.2.4
Summary: A commandline tool to search indexed webpages.
License: MIT
Author: Sander van Dragt
Author-email: sander@vandragt.com
Requires-Python: >=3.11,<3.12
Classifier: License :: OSI Approved :: MIT License
Classifier: Programming Language :: Python :: 3
Classifier: Programming Language :: Python :: 3.11
Requires-Dist: appdirs (>=1.4,<2.0)
Requires-Dist: click (>=8.0,<9.0)
Requires-Dist: newspaper3k (>=0.2,<0.3)
Requires-Dist: textual (>=0.1.18,<0.2.0)
